llama_index/readers/athena/__init__.py
llama_index/readers/athena/base.py
llama_index_readers_athena-0.4.1.dist-info/METADATA
llama_index_readers_athena-0.4.1.dist-info/WHEEL
llama_index_readers_athena-0.4.1.dist-info/licenses/LICENSE
llama_index_readers_athena-0.4.1.dist-info/RECORD
