Metadata-Version: 2.4
Name: llama-index-readers-athena
Version: 0.4.1
Summary: llama-index readers athena integration
Author-email: Your Name <you@example.com>
Maintainer: mattick27
License-Expression: MIT
License-File: LICENSE
Keywords: aws athena,datalake,sql
Requires-Python: <4.0,>=3.9
Requires-Dist: boto3<2,>=1.34.28
Requires-Dist: llama-index-core<0.15,>=0.13.0
Requires-Dist: pyathena<4,>=3.2.0
Requires-Dist: sqlalchemy<3,>=2.0.25
